erp_air/__init__.py
erp_air/custom_validators.py
erp_air/data_structs.py
erp_air/erp_utils.py
erp_air-0.0.4b0.dist-info/LICENSE
erp_air-0.0.4b0.dist-info/WHEEL
erp_air-0.0.4b0.dist-info/METADATA
erp_air-0.0.4b0.dist-info/RECORD
